harmonyqt/__about__.py
harmonyqt/__init__.py
harmonyqt/__main__.py
harmonyqt/accounts.py
harmonyqt/actions.py
harmonyqt/dock.py
harmonyqt/event_logger.py
harmonyqt/events.py
harmonyqt/homepage.py
harmonyqt/main.py
harmonyqt/markdown.py
harmonyqt/menu.py
harmonyqt/message.py
harmonyqt/shortcuts.py
harmonyqt/theming.py
harmonyqt/toolbar.py
harmonyqt/usertree.py
harmonyqt/utils.py
harmonyqt/chat/__init__.py
harmonyqt/chat/chat.py
harmonyqt/chat/display.py
harmonyqt/chat/dock.py
harmonyqt/chat/send_area.py
harmonyqt/commands/__init__.py
harmonyqt/commands/alias.py
harmonyqt/commands/autorun.py
harmonyqt/commands/devices.py
harmonyqt/commands/eval.py
harmonyqt/commands/help.py
harmonyqt/commands/nick.py
harmonyqt/commands/pdb.py
harmonyqt/commands/room_set.py
harmonyqt/commands/say.py
harmonyqt/commands/shell.py
harmonyqt/commands/utils.py
harmonyqt/dialogs/__init__.py
harmonyqt/dialogs/accept_room_invite.py
harmonyqt/dialogs/base.py
harmonyqt/dialogs/create_room.py
harmonyqt/dialogs/invite_to_room.py
harmonyqt/dialogs/login.py
harmonyqt/error_handler/__init__.py
harmonyqt/error_handler/boxes.py
harmonyqt/error_handler/console.py
harmonyqt/error_handler/display.py
harmonyqt/icons/flat_white/accept.png
harmonyqt/icons/flat_white/accept_small.png
harmonyqt/icons/flat_white/account_add.png
harmonyqt/icons/flat_white/account_del.png
harmonyqt/icons/flat_white/cancel.png
harmonyqt/icons/flat_white/cancel_small.png
harmonyqt/icons/flat_white/create_room.png
harmonyqt/icons/flat_white/default_avatar.png
harmonyqt/icons/flat_white/default_avatar_small.png
harmonyqt/icons/flat_white/direct_chat.png
harmonyqt/icons/flat_white/indicator_invite.png
harmonyqt/icons/flat_white/invite.png
harmonyqt/icons/flat_white/join_room.png
harmonyqt/icons/flat_white/leave.png
harmonyqt/icons/flat_white/login.png
harmonyqt/icons/flat_white/new_chat.png
harmonyqt/icons/flat_white/preferences.png
harmonyqt-0.5.8.dist-info/METADATA
harmonyqt-0.5.8.dist-info/RECORD
harmonyqt-0.5.8.dist-info/WHEEL
harmonyqt-0.5.8.dist-info/entry_points.txt
harmonyqt-0.5.8.dist-info/top_level.txt
