Metadata-Version: 2.1
Name: harmonyqt
Version: 0.5.8
Summary: Test Matrix client
Home-page: https://github.com/mirukan/harmonyqt
Author: miruka
Author-email: miruka@disroot.org
License: GPLv3
Keywords: <KEYWORDS>
Platform: UNKNOWN
Classifier: Development Status :: 3 - Alpha
Classifier: Intended Audience :: Developers
Classifier: Intended Audience :: End Users/Desktop
Classifier: Environment :: Console
Classifier: License :: OSI Approved :: GNU General Public License v3 or later (GPLv3+)
Classifier: Programming Language :: Python :: 3
Classifier: Programming Language :: Python :: 3 :: Only
Classifier: Programming Language :: Python :: 3.6
Classifier: Programming Language :: Python :: 3.7
Classifier: Natural Language :: English
Classifier: Operating System :: POSIX
Requires-Python: >=3.6, <4
Requires-Dist: PyQt5
Requires-Dist: atomicfile
Requires-Dist: docopt
Requires-Dist: matrix-client-harmonyqt[e2e] (>=0.4.2-dev-4)
Requires-Dist: setuptools
Requires-Dist: markdownify
Requires-Dist: markdown2
Requires-Dist: pygments
Requires-Dist: cachetools
Requires-Dist: kids.cache
Requires-Dist: dataclasses; python_version < "3.7"
